.hgignore
.hgtags
README
setup.py
docs/changes.rst
mr/__init__.py
mr.anderson.egg-info/PKG-INFO
mr.anderson.egg-info/SOURCES.txt
mr.anderson.egg-info/dependency_links.txt
mr.anderson.egg-info/entry_points.txt
mr.anderson.egg-info/not-zip-safe
mr.anderson.egg-info/requires.txt
mr.anderson.egg-info/top_level.txt
mr/anderson/__init__.py
mr/anderson/builder.py
mr/anderson/support.py
mr/anderson/testing.py
mr/anderson/tests.py
mr/anderson/static/bootstrap.py
mr/anderson/templates/3.x.cfg
mr/anderson/templates/4.x.cfg