Metadata-Version: 1.0
Name: mr.anderson
Version: 1.1.1
Summary: Plone testing matrix builder utility
Home-page: https://bitbucket.org/pumazi/mr.anderson
Author: Michael Mulich
Author-email: michael.mulich@gmail.com
License: GPL
Keywords: plone buildout
Platform: UNKNOWN
Classifier: Framework :: Plone
Classifier: Programming Language :: Python
Classifier: Intended Audience :: Developers
Classifier: Development Status :: 5 - Production/Stable
